LICENSE
MANIFEST.in
README.rst
setup.cfg
setup.py
resource_manager/__init__.py
resource_manager/console.py
resource_manager/exceptions.py
resource_manager/manager.py
resource_manager/parser.py
resource_manager/renderer.py
resource_manager/scope.py
resource_manager/utils.py
resource_manager/visitor.py
resource_manager/wrappers.py
resource_manager.egg-info/PKG-INFO
resource_manager.egg-info/SOURCES.txt
resource_manager.egg-info/dependency_links.txt
resource_manager.egg-info/entry_points.txt
resource_manager.egg-info/top_level.txt
resource_manager/semantics/__init__.py
resource_manager/semantics/analyzer.py
resource_manager/semantics/visitor.py