Metadata-Version: 1.1
Name: resource-manager
Version: 0.11.3
Summary: A small resource manager for config files
Home-page: https://github.com/maxme1/resource-manager
Author: maxme1
Author-email: maxs987@gmail.com
License: MIT
Download-URL: https://github.com/maxme1/resource-manager/archive/0.11.3.tar.gz
Keywords: config,lazy,interpreter
Platform: UNKNOWN
Classifier: Development Status :: 5 - Production/Stable
Classifier: Programming Language :: Python :: 3.4
Classifier: Programming Language :: Python :: 3.5
Classifier: Programming Language :: Python :: 3.6
Classifier: Programming Language :: Python :: 3.7
Classifier: Programming Language :: Python :: 3.8
Classifier: Programming Language :: Python :: 3.9
